pylogics/__init__.py
pylogics/exceptions.py
pylogics/helpers/__init__.py
pylogics/helpers/cache_hash.py
pylogics/helpers/misc.py
pylogics/parsers/__init__.py
pylogics/parsers/base.py
pylogics/parsers/ldl.lark
pylogics/parsers/ldl.py
pylogics/parsers/ltl.lark
pylogics/parsers/ltl.py
pylogics/parsers/pl.lark
pylogics/parsers/pl.py
pylogics/parsers/pltl.lark
pylogics/parsers/pltl.py
pylogics/semantics/__init__.py
pylogics/semantics/base.py
pylogics/semantics/pl.py
pylogics/syntax/__init__.py
pylogics/syntax/base.py
pylogics/syntax/ldl.py
pylogics/syntax/ltl.py
pylogics/syntax/pl.py
pylogics/syntax/pltl.py
pylogics/utils/__init__.py
pylogics/utils/to_string.py
pylogics-0.2.0.dist-info/LICENSE
pylogics-0.2.0.dist-info/METADATA
pylogics-0.2.0.dist-info/WHEEL
pylogics-0.2.0.dist-info/RECORD
