Metadata-Version: 2.1
Name: pylogics
Version: 0.2.0
Summary: A Python library for logic formalisms representation and manipulation.
Home-page: https://whitemech.github.io/pylogics
License: LGPL-3.0-or-later
Keywords: logic,propositional logic,predicate logic,temporal logic
Author: MarcoFavorito
Author-email: marco.favorito@gmail.com
Requires-Python: >=3.8.1,<4.0
Classifier: Development Status :: 2 - Pre-Alpha
Classifier: Intended Audience :: Developers
Classifier: License :: OSI Approved :: GNU Lesser General Public License v3 or later (LGPLv3+)
Classifier: Natural Language :: English
Classifier: Programming Language :: Python :: 3
Classifier: Programming Language :: Python :: 3.9
Classifier: Programming Language :: Python :: 3.10
Classifier: Programming Language :: Python :: 3.11
Classifier: Programming Language :: Python :: 3.8
Requires-Dist: lark (>=1.1.5,<2.0.0)
Project-URL: Bug Tracker, https://github.com/whitemech/pylogics/issues
Project-URL: Documentation, https://whitemech.github.io/pylogics
Project-URL: Pull Requests, https://github.com/whitemech/pylogics/pulls
Project-URL: Repository, https://github.com/whitemech/pylogics.git
